{
    "streams": [{
        "name": "28 irratia",
        "url": "https://radioserver11.profesionalhosting.com:19759/stream",
        "logo": "https://github.com/aldatsa/plugin.audio.euskarazko-irratiak/raw/master/streams/logos/28irratia.jpg"
    }, {
        "name": "97FM irratia",
        "url": "https://airtime.97irratia.info/radio-ssl.ogg",
        "logo": "https://github.com/aldatsa/plugin.audio.euskarazko-irratiak/raw/master/streams/logos/97fm-irratia.jpg"
    }, {
        "name": "Antxeta irratia",
        "url": "https://streaming.radiocast.pro:8443/antxeta",
        "logo": "https://github.com/aldatsa/plugin.audio.euskarazko-irratiak/raw/master/streams/logos/antxeta-irratia.png"
    }, {
        "name": "Arraio irratia",
        "url": "http://irratia.arraio.eus:9001/irratia.ogg",
        "logo": "https://github.com/aldatsa/plugin.audio.euskarazko-irratiak/raw/master/streams/logos/arraio-irratia.jpg"
    }, {
        "name": "Arrate irratia",
        "url": "http://5.135.155.232:8002/stream",
        "logo": "https://github.com/aldatsa/plugin.audio.euskarazko-irratiak/raw/master/streams/logos/arrate-irratia.jpg"
    }, {
        "name": "Ataria irratia",
        "url": "https://server8.emitironline.com:18444/stream",
        "logo": "https://github.com/aldatsa/plugin.audio.euskarazko-irratiak/raw/master/streams/logos/ataria-irratia.jpg"
    }, {
        "name": "Beleixe irratia",
        "url": "http://server8.20comunicacion.com:8016/",
        "logo": "https://github.com/aldatsa/plugin.audio.euskarazko-irratiak/raw/master/streams/logos/beleixe.jpeg"
    }, {
        "name": "Bilbo Hiria irratia",
        "url": "https://streaming.radiocast.pro:8443/bilbohiria",
        "logo": "https://github.com/aldatsa/plugin.audio.euskarazko-irratiak/raw/master/streams/logos/bilbo-hiria-irratia.gif"
    }, {
        "name": "Bizkaia irratia",
        "url": "https://nerbioi.radiopopular.eus/bizkaiairratia2",
        "logo": "https://github.com/aldatsa/plugin.audio.euskarazko-irratiak/raw/master/streams/logos/bizkaia-irratia.jpg"
    }, {
        "name": "Eguzki irratia",
        "url": "https://streaming.eguzki.eus/eguzki.mp3",
        "logo": "https://github.com/aldatsa/plugin.audio.euskarazko-irratiak/raw/master/streams/logos/eguzki-irratia.jpg"
    }, {
        "name": "Erlo irratia",
        "url": "https://radioserver11.profesionalhosting.com:19166/stream",
        "logo": "https://github.com/aldatsa/plugin.audio.euskarazko-irratiak/raw/master/streams/erlo.jpeg"
    }, {
        "name": "EITB irratia",
        "url": "https://live-dvr.eitb-fastly.cross-media.es/live-content/eitbmusika-hls/master.m3u8",
        "logo": "https://github.com/aldatsa/plugin.audio.euskarazko-irratiak/raw/master/streams/logos/eitb-irratia.jpg"
    }, {
        "name": "Esan Erran irratia",
        "url": "http://esanerran.ametza.eus/zuzenean.ogg",
        "logo": "https://github.com/aldatsa/plugin.audio.euskarazko-irratiak/raw/master/streams/logos/esan-erran-irratia.jpg"
    }, {
        "name": "Euskadi irratia",
        "url": "https://live-dvr.eitb-fastly.cross-media.es/live-content/euskadirratia-hls/master.m3u8",
        "logo": "https://github.com/aldatsa/plugin.audio.euskarazko-irratiak/raw/master/streams/logos/euskadi-irratia.jpg"
    }, {
        "name": "Euskalerria irratia",
        "url": "https://server9.emitironline.com:8014/stream",
        "logo": "https://github.com/aldatsa/plugin.audio.euskarazko-irratiak/raw/master/streams/logos/euskalerria-irratia.png"
    }, {
        "name": "Gaztea irratia",
        "url": "https://live-dvr.eitb-fastly.cross-media.es/live-content/gaztea-hls/master.m3u8",
        "logo": "https://github.com/aldatsa/plugin.audio.euskarazko-irratiak/raw/master/streams/logos/gaztea.jpg"
    }, {
        "name": "Goierri irratia",
        "url": "https://radioserver11.profesionalhosting.com:19142/stream",
        "logo": "https://github.com/aldatsa/plugin.audio.euskarazko-irratiak/raw/master/streams/logos/goierri-irratia.jpg"
    }, {
        "name": "Gure Irratia",
        "url": "http://heberg.radioludo.com:8007/stream",
        "logo": "https://github.com/aldatsa/plugin.audio.euskarazko-irratiak/raw/master/streams/logos/gure-irratia.jpeg"
    }, {
        "name": "Hala Bedi 1 irratia",
        "url": "https://halabedi.eus:8443/hb1_64.mp3",
        "logo": "https://github.com/aldatsa/plugin.audio.euskarazko-irratiak/raw/master/streams/logos/hala-bedi-irratia.png"
        }, {
        "name": "Hala Bedi 2 irratia",
        "url": "https://halabedi.eus:8443/hb2_64.mp3",
        "logo": "https://github.com/aldatsa/plugin.audio.euskarazko-irratiak/raw/master/streams/logos/hala-bedi-irratia.png"
    }, {
        "name": "Irati irratia",
        "url": "http://188.93.73.7:8102/stream",
        "logo": "https://github.com/aldatsa/plugin.audio.euskarazko-irratiak/raw/master/streams/logos/irati-irratia.gif"
    }, {
        "name": "Irola irratia",
        "url": "https://s.streampunk.cc/_stream/irola_irratia.mp3",
        "logo": "https://github.com/aldatsa/plugin.audio.euskarazko-irratiak/raw/master/streams/logos/irola-irratia.jpg"
    }, {
        "name": "Irulegiko irratia",
        "url": "http://heberg.radioludo.com:8007/stream2",
        "logo": "https://github.com/aldatsa/plugin.audio.euskarazko-irratiak/raw/master/streams/logos/irulegiko-irratia.jpg"
    }, {
        "name": "Kontrako eztarrixe irratia",
        "url": "http://zerb01.baibalab.net:8000/keztarri.mp3",
        "logo": "https://github.com/aldatsa/plugin.audio.euskarazko-irratiak/raw/master/streams/logos/kontrako-eztarrixe-irratia.png"
    }, {
        "name": "Miribilla irratia",
        "url": "http://bizkaia.dyndns.org:8011/;stream.mp3",
        "logo": "https://github.com/aldatsa/plugin.audio.euskarazko-irratiak/raw/master/streams/logos/miribilla-irratia.png"
    }, {
        "name": "Naiz irratia",
        "url": "https://zuzenean.naiz.eus/naiz_irratia.mp3",
        "logo": "https://gitlab.com/aldatsa/plugin.audio.euskarazko-irratiak/-/raw/master/streams/logos/naiz-irratia.png"
    }, {
        "name": "Oiartzun irratia",
        "url": "http://176.9.123.4:55019/;stream.mp3",
        "logo": "https://github.com/aldatsa/plugin.audio.euskarazko-irratiak/raw/master/streams/logos/oiartzun-irratia.jpg"
    }, {
        "name": "Radio Kultura irratia",
        "url": "http://94.23.27.6:8254/live.m3u",
        "logo": "https://github.com/aldatsa/plugin.audio.euskarazko-irratiak/raw/master/streams/logos/radio-kultura-irratia.gif"
    }, {
        "name": "Radixu irratia",
        "url": "http://zuzenean.radixu.info:8000/radixu-live-128",
        "logo": "https://github.com/aldatsa/plugin.audio.euskarazko-irratiak/raw/master/streams/logos/radixu-irratia.png"
    }, {
        "name": "Ttan Ttakun irratia",
        "url": "https://ttanttakun.eus/stream/ttanttakun.ogg",
        "logo": "https://github.com/aldatsa/plugin.audio.euskarazko-irratiak/raw/master/streams/logos/ttan-ttakun-irratia.png"
    }, {
        "name": "Txapa irratia",
        "url": "http://halabedi.eus:8000/txapa.mp3",
        "logo": "https://github.com/aldatsa/plugin.audio.euskarazko-irratiak/raw/master/streams/logos/txapa-irratia.png"
    }, {
        "name": "Xiberoko Botza",
        "url": "http://87.106.192.209:8001/xiberokobotza.mp3",
        "logo": "https://github.com/aldatsa/plugin.audio.euskarazko-irratiak/raw/master/streams/logos/xiberoko-botza.png"
    }, {
        "name": "Xorroxin irratia",
        "url": "https://xorroxinirratia.streaming-pro.com:6002/xorroxinirratia.mp3",
        "logo": "https://github.com/aldatsa/plugin.audio.euskarazko-irratiak/raw/master/streams/logos/xorroxin-irratia.jpeg"
    }, {
        "name": "Zintzilik irratia",
        "url": "http://irratia.zintzilik.net/zintzilik.ogg",
        "logo": "https://github.com/aldatsa/plugin.audio.euskarazko-irratiak/raw/master/streams/logos/zintzilik-irratia.png"
    }]
}
